Day08/seven_segment_decoder.v
// 7-Segment Display Decoder
module seven_segment_decoder (
    input wire [3:0] bcd,
    output reg [6:0] seg 
);

    always @(*) begin
        case (bcd)
            4'b0000: seg = 7'b1111110; // 0
            4'b0001: seg = 7'b0110000; // 1
            4'b0010: seg = 7'b1101101; // 2
            4'b0011: seg = 7'b1111001; // 3
            4'b0100: seg = 7'b0110011; // 4
            4'b0101: seg = 7'b1011011; // 5
            4'b0110: seg = 7'b1011111; // 6
            4'b0111: seg = 7'b1110000; // 7
            4'b1000: seg = 7'b1111111; // 8
            4'b1001: seg = 7'b1111011; // 9
            default: seg = 7'b0000000; // Blank for invalid input
        endcase
    end

endmodule

Day08/testbench.v
`timescale 1ns / 1ps

// Testbench for 7-Segment Display Decoder
module tb_seven_segment_decoder;

    reg [3:0] bcd;          
    wire [6:0] seg;         

    // Instantiate the decoder module
    seven_segment_decoder uut (
        .bcd(bcd),
        .seg(seg)
    );

    integer i;

    initial begin
        
        $dumpfile("seven_segment_decoder.vcd");
        $dumpvars(0, tb_seven_segment_decoder);

        
        for (i = 0; i < 16; i = i + 1) begin
            bcd = i[3:0];   // Assign 4-bit value
            #10;            // Wait for 10 time units
        end

        #10 $finish;
    end

endmodule


/*
Here’s your updated tracker:

| Day | Project Name              | Description                                                             | Link                                       |
|-----|---------------------------|-------------------------------------------------------------------------|--------------------------------------------|
|  1  | Basic Logic Gates         | AND, OR, NOT, XOR, XNOR, NOR                                           | [Day 1 - Basic Gates](./Day01)            |
|  2  | 4-Input AND, BCD Adder, Ripple Carry Adder | Implementation of a 4-input AND gate, BCD adder with correction logic, and a 4-bit ripple carry adder | [Day 2 - Adders and AND Gate](./Day02)    |
|  3  | 4:1 Multiplexer, Carry Look-Ahead Adder | Designed a 4:1 MUX and implemented a carry look-ahead adder                    | [Day 3 - MUX and Carry Look-Ahead Adder](./Day03) |
|  4  | Magnitude Comparator       | 2-bit Magnitude Comparator                                             | [Day 4 - Comparator](./Day04)             |
|  5  | 3-to-8 Decoder             | Implemented a 3-to-8 Decoder with enable signal                        | [Day 5 - Decoder](./Day05)                |
|  6  | 4-Bit Signed Comparator    | Designed a comparator for signed 4-bit numbers                        | [Day 6 - Signed Comparator](./Day06)      |
|  7  | 4-Bit Subtractor           | Created a 4-bit subtractor using 2's complement logic                  | [Day 7 - Subtractor](./Day07)             |
|  8  | 7-Segment Display Decoder  | Developed a BCD-to-7-segment display decoder for numeric visualization | [Day 8 - Seven Segment Decoder](./Day08)  |
*/

Day08/seven_segment_decoder.vcd
$date
	Sat Jan 18 20:34:08 2025
$end
$version
	Icarus Verilog
$end
$timescale
	1ps
$end
$scope module tb_seven_segment_decoder $end
$var wire 7 ! seg [6:0] $end
$var reg 4 " bcd [3:0] $end
$var integer 32 # i [31:0] $end
$scope module uut $end
$var wire 4 $ bcd [3:0] $end
$var reg 7 % seg [6:0] $end
$upscope $end
$upscope $end
$enddefinitions $end
$comment Show the parameter values. $end
$dumpall
$end
#0
$dumpvars
b1111110 %
b0 $
b0 #
b0 "
b1111110 !
$end
#10000
b110000 !
b110000 %
b1 "
b1 $
b1 #
#20000
b1101101 !
b1101101 %
b10 "
b10 $
b10 #
#30000
b1111001 !
b1111001 %
b11 "
b11 $
b11 #
#40000
b110011 !
b110011 %
b100 "
b100 $
b100 #
#50000
b1011011 !
b1011011 %
b101 "
b101 $
b101 #
#60000
b1011111 !
b1011111 %
b110 "
b110 $
b110 #
#70000
b1110000 !
b1110000 %
b111 "
b111 $
b111 #
#80000
b1111111 !
b1111111 %
b1000 "
b1000 $
b1000 #
#90000
b1111011 !
b1111011 %
b1001 "
b1001 $
b1001 #
#100000
b0 !
b0 %
b1010 "
b1010 $
b1010 #
#110000
b1011 "
b1011 $
b1011 #
#120000
b1100 "
b1100 $
b1100 #
#130000
b1101 "
b1101 $
b1101 #
#140000
b1110 "
b1110 $
b1110 #
#150000
b1111 "
b1111 $
b1111 #
#160000
b10000 #
