Day10/priority_encoder.v
module priority_encoder (
    input wire [3:0] in,    
    output reg [1:0] out,   
    output reg valid        
);

    always @(*) begin
        if (in[3]) begin
            out = 2'b11;    // Highest priority
            valid = 1'b1;
        end else if (in[2]) begin
            out = 2'b10;
            valid = 1'b1;
        end else if (in[1]) begin
            out = 2'b01;
            valid = 1'b1;
        end else if (in[0]) begin
            out = 2'b00;
            valid = 1'b1;
        end else begin
            out = 2'b00;    // Default output
            valid = 1'b0;   // No valid input
        end
    end

endmodule

Day10/testbench.v
`timescale 1ns / 1ps

module tb_priority_encoder;

    reg [3:0] in;          
    wire [1:0] out;        
    wire valid;            

    // Instantiate the priority encoder module
    priority_encoder uut (
        .in(in),
        .out(out),
        .valid(valid)
    );

    integer i;

    initial begin
        $dumpfile("priority_encoder.vcd");
        $dumpvars(0, tb_priority_encoder);

        // Test all possible input combinations
        for (i = 0; i < 16; i = i + 1) begin
            in = i[3:0];    
            #10;            
        end

        #10 $finish;        // End simulation
    end

endmodule

Day10/priority_encoder.vcd
$date
	Mon Jan 20 22:43:23 2025
$end
$version
	Icarus Verilog
$end
$timescale
	1ps
$end
$scope module tb_priority_encoder $end
$var wire 1 ! valid $end
$var wire 2 " out [1:0] $end
$var reg 4 # in [3:0] $end
$var integer 32 $ i [31:0] $end
$scope module uut $end
$var wire 4 % in [3:0] $end
$var reg 2 & out [1:0] $end
$var reg 1 ! valid $end
$upscope $end
$upscope $end
$enddefinitions $end
$comment Show the parameter values. $end
$dumpall
$end
#0
$dumpvars
b0 &
b0 %
b0 $
b0 #
b0 "
0!
$end
#10000
1!
b1 #
b1 %
b1 $
#20000
b1 "
b1 &
b10 #
b10 %
b10 $
#30000
b11 #
b11 %
b11 $
#40000
b10 "
b10 &
b100 #
b100 %
b100 $
#50000
b101 #
b101 %
b101 $
#60000
b110 #
b110 %
b110 $
#70000
b111 #
b111 %
b111 $
#80000
b11 "
b11 &
b1000 #
b1000 %
b1000 $
#90000
b1001 #
b1001 %
b1001 $
#100000
b1010 #
b1010 %
b1010 $
#110000
b1011 #
b1011 %
b1011 $
#120000
b1100 #
b1100 %
b1100 $
#130000
b1101 #
b1101 %
b1101 $
#140000
b1110 #
b1110 %
b1110 $
#150000
b1111 #
b1111 %
b1111 $
#160000
b10000 $
