Day02/BCD Adder/bcd_adder.v
module bcd_adder(a, b, cin, sum, cout);
    input [3:0] a, b;
    input cin;
    output [3:0] sum;
    output cout;

    wire [4:0] temp_sum;
    wire [3:0] correction;
    wire carry_correction;

    assign temp_sum = a + b + cin;
    assign correction = (temp_sum > 9) ? 4'b0110 : 4'b0000; //if temp_sum is greater than 9, then we add 6(decimal) to the sum else add 0
    assign carry_correction = (temp_sum > 9) ? 1 : 0; //if temp_sum is greater than 9, then we add 1 to the cout else add 0
    assign sum = temp_sum[3:0] + correction;
    assign cout = temp_sum[4] | carry_correction;
    
endmodule
/*
        The above logic can also be written as:
        if (temp_sum > 9)
            begin
             assign correction = sum + 4'b0110;
             assign carry_correction = 1;
             assign sum = temp_sum[3:0] + correction;
             assign cout = temp_sum[4] | carry_correction;
        end

        else
            begin
             assign sum = temp_sum[3:0];
             assign cout = temp_sum[4];
            end

    */

Day02/BCD Adder/tb_bcd_adder.v
module tb_bcd_adder;
    reg [3:0] a, b;
    reg cin;
    wire [3:0] sum;
    wire cout;

    bcd_adder uut(.a(a), .b(b), .cin(cin), .sum(sum), .cout(cout));

    initial begin
        $dumpfile("bcd_adder.vcd");
        $dumpvars(0, tb_bcd_adder);
        for (integer i = 0; i < 10; i = i + 1) begin
            for (integer j = 0; j < 10; j = j + 1) 
            begin
                a = i; b = j; cin = 0; #10;
                a = i; b = j; cin = 1; #10;
            end
        end
        $finish;
    end
endmodule

Day02/BCD Adder/bcd_adder.vcd
$date
	Sun Jan 12 13:12:50 2025
$end
$version
	Icarus Verilog
$end
$timescale
	1s
$end
$scope module tb_bcd_adder $end
$var wire 4 ! sum [3:0] $end
$var wire 1 " cout $end
$var reg 4 # a [3:0] $end
$var reg 4 $ b [3:0] $end
$var reg 1 % cin $end
$scope module uut $end
$var wire 4 & a [3:0] $end
$var wire 4 ' b [3:0] $end
$var wire 1 % cin $end
$var wire 1 " cout $end
$var wire 5 ( temp_sum [4:0] $end
$var wire 4 ) sum [3:0] $end
$var wire 4 * correction [3:0] $end
$var wire 1 + carry_correction $end
$upscope $end
$scope begin $ivl_for_loop0 $end
$var integer 32 , i [31:0] $end
$scope begin $ivl_for_loop1 $end
$var integer 32 - j [31:0] $end
$upscope $end
$upscope $end
$upscope $end
$enddefinitions $end
$comment Show the parameter values. $end
$dumpall
$end
#0
$dumpvars
b0 -
b0 ,
0+
b0 *
b0 )
b0 (
b0 '
b0 &
0%
b0 $
b0 #
0"
b0 !
$end
#10
b1 !
b1 )
b1 (
1%
#20
0%
b1 (
b1 $
b1 '
b1 -
#30
b10 !
b10 )
b10 (
1%
#40
0%
b10 (
b10 $
b10 '
b10 -
#50
b11 !
b11 )
b11 (
1%
#60
0%
b11 (
b11 $
b11 '
b11 -
#70
b100 !
b100 )
b100 (
1%
#80
0%
b100 (
b100 $
b100 '
b100 -
#90
b101 !
b101 )
b101 (
1%
#100
0%
b101 (
b101 $
b101 '
b101 -
#110
b110 !
b110 )
b110 (
1%
#120
0%
b110 (
b110 $
b110 '
b110 -
#130
b111 !
b111 )
b111 (
1%
#140
0%
b111 (
b111 $
b111 '
b111 -
#150
b1000 !
b1000 )
b1000 (
1%
#160
0%
b1000 (
b1000 $
b1000 '
b1000 -
#170
b1001 !
b1001 )
b1001 (
1%
#180
0%
b1001 (
b1001 $
b1001 '
b1001 -
#190
1"
1+
b110 *
b0 !
b0 )
b1010 (
1%
#200
0"
0+
b0 *
b1 !
b1 )
0%
b0 $
b0 '
b1 (
b1 #
b1 &
b1 ,
b0 -
#210
b10 !
b10 )
b10 (
1%
#220
0%
b10 (
b1 $
b1 '
b1 -
#230
b11 !
b11 )
b11 (
1%
#240
0%
b11 (
b10 $
b10 '
b10 -
#250
b100 !
b100 )
b100 (
1%
#260
0%
b100 (
b11 $
b11 '
b11 -
#270
b101 !
b101 )
b101 (
1%
#280
0%
b101 (
b100 $
b100 '
b100 -
#290
b110 !
b110 )
b110 (
1%
#300
0%
b110 (
b101 $
b101 '
b101 -
#310
b111 !
b111 )
b111 (
1%
#320
0%
b111 (
b110 $
b110 '
b110 -
#330
b1000 !
b1000 )
b1000 (
1%
#340
0%
b1000 (
b111 $
b111 '
b111 -
#350
b1001 !
b1001 )
b1001 (
1%
#360
0%
b1001 (
b1000 $
b1000 '
b1000 -
#370
1"
1+
b110 *
b0 !
b0 )
b1010 (
1%
#380
0%
b1010 (
b1001 $
b1001 '
b1001 -
#390
b1 !
b1 )
b1011 (
1%
#400
0"
0+
b0 *
b10 !
b10 )
0%
b0 $
b0 '
b10 (
b10 #
b10 &
b10 ,
b0 -
#410
b11 !
b11 )
b11 (
1%
#420
0%
b11 (
b1 $
b1 '
b1 -
#430
b100 !
b100 )
b100 (
1%
#440
0%
b100 (
b10 $
b10 '
b10 -
#450
b101 !
b101 )
b101 (
1%
#460
0%
b101 (
b11 $
b11 '
b11 -
#470
b110 !
b110 )
b110 (
1%
#480
0%
b110 (
b100 $
b100 '
b100 -
#490
b111 !
b111 )
b111 (
1%
#500
0%
b111 (
b101 $
b101 '
b101 -
#510
b1000 !
b1000 )
b1000 (
1%
#520
0%
b1000 (
b110 $
b110 '
b110 -
#530
b1001 !
b1001 )
b1001 (
1%
#540
0%
b1001 (
b111 $
b111 '
b111 -
#550
1"
1+
b110 *
b0 !
b0 )
b1010 (
1%
#560
0%
b1010 (
b1000 $
b1000 '
b1000 -
#570
b1 !
b1 )
b1011 (
1%
#580
0%
b1011 (
b1001 $
b1001 '
b1001 -
#590
b10 !
b10 )
b1100 (
1%
#600
0"
0+
b0 *
b11 !
b11 )
0%
b0 $
b0 '
b11 (
b11 #
b11 &
b11 ,
b0 -
#610
b100 !
b100 )
b100 (
1%
#620
0%
b100 (
b1 $
b1 '
b1 -
#630
b101 !
b101 )
b101 (
1%
#640
0%
b101 (
b10 $
b10 '
b10 -
#650
b110 !
b110 )
b110 (
1%
#660
0%
b110 (
b11 $
b11 '
b11 -
#670
b111 !
b111 )
b111 (
1%
#680
0%
b111 (
b100 $
b100 '
b100 -
#690
b1000 !
b1000 )
b1000 (
1%
#700
0%
b1000 (
b101 $
b101 '
b101 -
#710
b1001 !
b1001 )
b1001 (
1%
#720
0%
b1001 (
b110 $
b110 '
b110 -
#730
1"
1+
b110 *
b0 !
b0 )
b1010 (
1%
#740
0%
b1010 (
b111 $
b111 '
b111 -
#750
b1 !
b1 )
b1011 (
1%
#760
0%
b1011 (
b1000 $
b1000 '
b1000 -
#770
b10 !
b10 )
b1100 (
1%
#780
0%
b1100 (
b1001 $
b1001 '
b1001 -
#790
b11 !
b11 )
b1101 (
1%
#800
0"
0+
b0 *
b100 !
b100 )
0%
b0 $
b0 '
b100 (
b100 #
b100 &
b100 ,
b0 -
#810
b101 !
b101 )
b101 (
1%
#820
0%
b101 (
b1 $
b1 '
b1 -
#830
b110 !
b110 )
b110 (
1%
#840
0%
b110 (
b10 $
b10 '
b10 -
#850
b111 !
b111 )
b111 (
1%
#860
0%
b111 (
b11 $
b11 '
b11 -
#870
b1000 !
b1000 )
b1000 (
1%
#880
0%
b1000 (
b100 $
b100 '
b100 -
#890
b1001 !
b1001 )
b1001 (
1%
#900
0%
b1001 (
b101 $
b101 '
b101 -
#910
1"
1+
b110 *
b0 !
b0 )
b1010 (
1%
#920
0%
b1010 (
b110 $
b110 '
b110 -
#930
b1 !
b1 )
b1011 (
1%
#940
0%
b1011 (
b111 $
b111 '
b111 -
#950
b10 !
b10 )
b1100 (
1%
#960
0%
b1100 (
b1000 $
b1000 '
b1000 -
#970
b11 !
b11 )
b1101 (
1%
#980
0%
b1101 (
b1001 $
b1001 '
b1001 -
#990
b100 !
b100 )
b1110 (
1%
#1000
0"
0+
b0 *
b101 !
b101 )
0%
b0 $
b0 '
b101 (
b101 #
b101 &
b101 ,
b0 -
#1010
b110 !
b110 )
b110 (
1%
#1020
0%
b110 (
b1 $
b1 '
b1 -
#1030
b111 !
b111 )
b111 (
1%
#1040
0%
b111 (
b10 $
b10 '
b10 -
#1050
b1000 !
b1000 )
b1000 (
1%
#1060
0%
b1000 (
b11 $
b11 '
b11 -
#1070
b1001 !
b1001 )
b1001 (
1%
#1080
0%
b1001 (
b100 $
b100 '
b100 -
#1090
1"
1+
b110 *
b0 !
b0 )
b1010 (
1%
#1100
0%
b1010 (
b101 $
b101 '
b101 -
#1110
b1 !
b1 )
b1011 (
1%
#1120
0%
b1011 (
b110 $
b110 '
b110 -
#1130
b10 !
b10 )
b1100 (
1%
#1140
0%
b1100 (
b111 $
b111 '
b111 -
#1150
b11 !
b11 )
b1101 (
1%
#1160
0%
b1101 (
b1000 $
b1000 '
b1000 -
#1170
b100 !
b100 )
b1110 (
1%
#1180
0%
b1110 (
b1001 $
b1001 '
b1001 -
#1190
b101 !
b101 )
b1111 (
1%
#1200
0"
0+
b0 *
b110 !
b110 )
0%
b0 $
b0 '
b110 (
b110 #
b110 &
b110 ,
b0 -
#1210
b111 !
b111 )
b111 (
1%
#1220
0%
b111 (
b1 $
b1 '
b1 -
#1230
b1000 !
b1000 )
b1000 (
1%
#1240
0%
b1000 (
b10 $
b10 '
b10 -
#1250
b1001 !
b1001 )
b1001 (
1%
#1260
0%
b1001 (
b11 $
b11 '
b11 -
#1270
1"
1+
b110 *
b0 !
b0 )
b1010 (
1%
#1280
0%
b1010 (
b100 $
b100 '
b100 -
#1290
b1 !
b1 )
b1011 (
1%
#1300
0%
b1011 (
b101 $
b101 '
b101 -
#1310
b10 !
b10 )
b1100 (
1%
#1320
0%
b1100 (
b110 $
b110 '
b110 -
#1330
b11 !
b11 )
b1101 (
1%
#1340
0%
b1101 (
b111 $
b111 '
b111 -
#1350
b100 !
b100 )
b1110 (
1%
#1360
0%
b1110 (
b1000 $
b1000 '
b1000 -
#1370
b101 !
b101 )
b1111 (
1%
#1380
0%
b1111 (
b1001 $
b1001 '
b1001 -
#1390
b110 !
b110 )
b10000 (
1%
#1400
0"
0+
b0 *
b111 !
b111 )
0%
b0 $
b0 '
b111 (
b111 #
b111 &
b111 ,
b0 -
#1410
b1000 !
b1000 )
b1000 (
1%
#1420
0%
b1000 (
b1 $
b1 '
b1 -
#1430
b1001 !
b1001 )
b1001 (
1%
#1440
0%
b1001 (
b10 $
b10 '
b10 -
#1450
1"
1+
b110 *
b0 !
b0 )
b1010 (
1%
#1460
0%
b1010 (
b11 $
b11 '
b11 -
#1470
b1 !
b1 )
b1011 (
1%
#1480
0%
b1011 (
b100 $
b100 '
b100 -
#1490
b10 !
b10 )
b1100 (
1%
#1500
0%
b1100 (
b101 $
b101 '
b101 -
#1510
b11 !
b11 )
b1101 (
1%
#1520
0%
b1101 (
b110 $
b110 '
b110 -
#1530
b100 !
b100 )
b1110 (
1%
#1540
0%
b1110 (
b111 $
b111 '
b111 -
#1550
b101 !
b101 )
b1111 (
1%
#1560
0%
b1111 (
b1000 $
b1000 '
b1000 -
#1570
b110 !
b110 )
b10000 (
1%
#1580
0%
b10000 (
b1001 $
b1001 '
b1001 -
#1590
b111 !
b111 )
b10001 (
1%
#1600
0"
0+
b0 *
b1000 !
b1000 )
0%
b0 $
b0 '
b1000 (
b1000 #
b1000 &
b1000 ,
b0 -
#1610
b1001 !
b1001 )
b1001 (
1%
#1620
0%
b1001 (
b1 $
b1 '
b1 -
#1630
1"
1+
b110 *
b0 !
b0 )
b1010 (
1%
#1640
0%
b1010 (
b10 $
b10 '
b10 -
#1650
b1 !
b1 )
b1011 (
1%
#1660
0%
b1011 (
b11 $
b11 '
b11 -
#1670
b10 !
b10 )
b1100 (
1%
#1680
0%
b1100 (
b100 $
b100 '
b100 -
#1690
b11 !
b11 )
b1101 (
1%
#1700
0%
b1101 (
b101 $
b101 '
b101 -
#1710
b100 !
b100 )
b1110 (
1%
#1720
0%
b1110 (
b110 $
b110 '
b110 -
#1730
b101 !
b101 )
b1111 (
1%
#1740
0%
b1111 (
b111 $
b111 '
b111 -
#1750
b110 !
b110 )
b10000 (
1%
#1760
0%
b10000 (
b1000 $
b1000 '
b1000 -
#1770
b111 !
b111 )
b10001 (
1%
#1780
0%
b10001 (
b1001 $
b1001 '
b1001 -
#1790
b1000 !
b1000 )
b10010 (
1%
#1800
0"
0+
b0 *
b1001 !
b1001 )
0%
b0 $
b0 '
b1001 (
b1001 #
b1001 &
b1001 ,
b0 -
#1810
1"
1+
b110 *
b0 !
b0 )
b1010 (
1%
#1820
0%
b1010 (
b1 $
b1 '
b1 -
#1830
b1 !
b1 )
b1011 (
1%
#1840
0%
b1011 (
b10 $
b10 '
b10 -
#1850
b10 !
b10 )
b1100 (
1%
#1860
0%
b1100 (
b11 $
b11 '
b11 -
#1870
b11 !
b11 )
b1101 (
1%
#1880
0%
b1101 (
b100 $
b100 '
b100 -
#1890
b100 !
b100 )
b1110 (
1%
#1900
0%
b1110 (
b101 $
b101 '
b101 -
#1910
b101 !
b101 )
b1111 (
1%
#1920
0%
b1111 (
b110 $
b110 '
b110 -
#1930
b110 !
b110 )
b10000 (
1%
#1940
0%
b10000 (
b111 $
b111 '
b111 -
#1950
b111 !
b111 )
b10001 (
1%
#1960
0%
b10001 (
b1000 $
b1000 '
b1000 -
#1970
b1000 !
b1000 )
b10010 (
1%
#1980
0%
b10010 (
b1001 $
b1001 '
b1001 -
#1990
b1001 !
b1001 )
b10011 (
1%
#2000
b1010 ,
b1010 -
