Day02/Ripple_Carry_Adder/ripple_carry_adder.v
module ripple_carry_adder(a, b, cin, sum, cout);
    input [3:0] a, b;
    input cin;
    output [3:0] sum;
    output cout;

    wire c1, c2, c3;

    full_adder fa0(a[0], b[0], cin, sum[0], c1);
    full_adder fa1(a[1], b[1], c1, sum[1], c2);
    full_adder fa2(a[2], b[2], c2, sum[2], c3);
    full_adder fa3(a[3], b[3], c3, sum[3], cout);
endmodule

module full_adder(a, b, cin, sum, cout);
    input a, b, cin;
    output sum, cout;

    assign sum = a ^ b ^ cin;
    assign cout = (a & b) | (b & cin) | (cin & a);
endmodule

Day02/Ripple_Carry_Adder/tb_ripple_carry_adder.v
module tb_ripple_carry_adder;
    reg [3:0] a, b;
    reg cin;
    wire [3:0] sum;
    wire cout;

    ripple_carry_adder uut(.a(a), .b(b), .cin(cin), .sum(sum), .cout(cout));

    initial begin
        $dumpfile("ripple_carry_adder.vcd");
        $dumpvars(0, tb_ripple_carry_adder);
        for (integer i = 0; i < 16; i = i + 1) begin
            for (integer j = 0; j < 16; j = j + 1) 
            begin
                a = i; b = j; cin = 0; #10;
                a = i; b = j; cin = 1; #10;
            end
        end
        $finish;
    end
endmodule

Day02/Ripple_Carry_Adder/ripple_carry_adder.vcd
$date
	Sun Jan 12 13:24:20 2025
$end
$version
	Icarus Verilog
$end
$timescale
	1s
$end
$scope module tb_ripple_carry_adder $end
$var wire 4 ! sum [3:0] $end
$var wire 1 " cout $end
$var reg 4 # a [3:0] $end
$var reg 4 $ b [3:0] $end
$var reg 1 % cin $end
$scope module uut $end
$var wire 4 & a [3:0] $end
$var wire 4 ' b [3:0] $end
$var wire 1 % cin $end
$var wire 4 ( sum [3:0] $end
$var wire 1 " cout $end
$var wire 1 ) c3 $end
$var wire 1 * c2 $end
$var wire 1 + c1 $end
$scope module fa0 $end
$var wire 1 , a $end
$var wire 1 - b $end
$var wire 1 % cin $end
$var wire 1 + cout $end
$var wire 1 . sum $end
$upscope $end
$scope module fa1 $end
$var wire 1 / a $end
$var wire 1 0 b $end
$var wire 1 + cin $end
$var wire 1 * cout $end
$var wire 1 1 sum $end
$upscope $end
$scope module fa2 $end
$var wire 1 2 a $end
$var wire 1 3 b $end
$var wire 1 * cin $end
$var wire 1 ) cout $end
$var wire 1 4 sum $end
$upscope $end
$scope module fa3 $end
$var wire 1 5 a $end
$var wire 1 6 b $end
$var wire 1 ) cin $end
$var wire 1 " cout $end
$var wire 1 7 sum $end
$upscope $end
$upscope $end
$scope begin $ivl_for_loop0 $end
$var integer 32 8 i [31:0] $end
$scope begin $ivl_for_loop1 $end
$var integer 32 9 j [31:0] $end
$upscope $end
$upscope $end
$upscope $end
$enddefinitions $end
$comment Show the parameter values. $end
$dumpall
$end
#0
$dumpvars
b0 9
b0 8
07
06
05
04
03
02
01
00
0/
0.
0-
0,
0+
0*
0)
b0 (
b0 '
b0 &
0%
b0 $
b0 #
0"
b0 !
$end
#10
b1 !
b1 (
1.
1%
#20
b1 !
b1 (
1.
1-
0%
b1 $
b1 '
b1 9
#30
11
1+
b10 !
b10 (
0.
1%
#40
04
0*
0+
11
b10 !
b10 (
0.
0-
10
0%
b10 $
b10 '
b10 9
#50
b11 !
b11 (
1.
1%
#60
b11 !
b11 (
1.
1-
0%
b11 $
b11 '
b11 9
#70
14
1*
01
1+
b100 !
b100 (
0.
1%
#80
07
0*
0)
0+
01
14
b100 !
b100 (
0.
0-
00
13
0%
b100 $
b100 '
b100 9
#90
b101 !
b101 (
1.
1%
#100
b101 !
b101 (
1.
1-
0%
b101 $
b101 '
b101 9
#110
11
1+
b110 !
b110 (
0.
1%
#120
07
0)
14
0*
0+
11
b110 !
b110 (
0.
0-
10
0%
b110 $
b110 '
b110 9
#130
b111 !
b111 (
1.
1%
#140
b111 !
b111 (
1.
1-
0%
b111 $
b111 '
b111 9
#150
17
1)
04
1*
01
1+
b1000 !
b1000 (
0.
1%
#160
0*
0)
0"
0+
01
04
17
b1000 !
b1000 (
0.
0-
00
03
16
0%
b1000 $
b1000 '
b1000 9
#170
b1001 !
b1001 (
1.
1%
#180
b1001 !
b1001 (
1.
1-
0%
b1001 $
b1001 '
b1001 9
#190
11
1+
b1010 !
b1010 (
0.
1%
#200
04
0*
0+
11
b1010 !
b1010 (
0.
0-
10
0%
b1010 $
b1010 '
b1010 9
#210
b1011 !
b1011 (
1.
1%
#220
b1011 !
b1011 (
1.
1-
0%
b1011 $
b1011 '
b1011 9
#230
14
1*
01
1+
b1100 !
b1100 (
0.
1%
#240
0"
17
0*
0)
0+
01
14
b1100 !
b1100 (
0.
0-
00
13
0%
b1100 $
b1100 '
b1100 9
#250
b1101 !
b1101 (
1.
1%
#260
b1101 !
b1101 (
1.
1-
0%
b1101 $
b1101 '
b1101 9
#270
11
1+
b1110 !
b1110 (
0.
1%
#280
0"
17
0)
14
0*
0+
11
b1110 !
b1110 (
0.
0-
10
0%
b1110 $
b1110 '
b1110 9
#290
b1111 !
b1111 (
1.
1%
#300
b1111 !
b1111 (
1.
1-
0%
b1111 $
b1111 '
b1111 9
#310
1"
07
1)
04
1*
01
1+
b0 !
b0 (
0.
1%
#320
0*
0)
0"
0+
01
04
07
b1 !
b1 (
1.
0-
00
03
06
1,
0%
b0 $
b0 '
b1 #
b1 &
b1 8
b0 9
#330
11
1+
b10 !
b10 (
0.
1%
#340
11
1+
b10 !
b10 (
0.
1-
0%
b1 $
b1 '
b1 9
#350
b11 !
b11 (
1.
1%
#360
04
0*
0+
11
b11 !
b11 (
1.
0-
10
0%
b10 $
b10 '
b10 9
#370
14
1*
01
1+
b100 !
b100 (
0.
1%
#380
14
1*
01
1+
b100 !
b100 (
0.
1-
0%
b11 $
b11 '
b11 9
#390
b101 !
b101 (
1.
1%
#400
07
0*
0)
0+
01
14
b101 !
b101 (
1.
0-
00
13
0%
b100 $
b100 '
b100 9
#410
11
1+
b110 !
b110 (
0.
1%
#420
11
1+
b110 !
b110 (
0.
1-
0%
b101 $
b101 '
b101 9
#430
b111 !
b111 (
1.
1%
#440
07
0)
14
0*
0+
11
b111 !
b111 (
1.
0-
10
0%
b110 $
b110 '
b110 9
#450
17
1)
04
1*
01
1+
b1000 !
b1000 (
0.
1%
#460
17
1)
04
1*
01
1+
b1000 !
b1000 (
0.
1-
0%
b111 $
b111 '
b111 9
#470
b1001 !
b1001 (
1.
1%
#480
0*
0)
0"
0+
01
04
17
b1001 !
b1001 (
1.
0-
00
03
16
0%
b1000 $
b1000 '
b1000 9
#490
11
1+
b1010 !
b1010 (
0.
1%
#500
11
1+
b1010 !
b1010 (
0.
1-
0%
b1001 $
b1001 '
b1001 9
#510
b1011 !
b1011 (
1.
1%
#520
04
0*
0+
11
b1011 !
b1011 (
1.
0-
10
0%
b1010 $
b1010 '
b1010 9
#530
14
1*
01
1+
b1100 !
b1100 (
0.
1%
#540
14
1*
01
1+
b1100 !
b1100 (
0.
1-
0%
b1011 $
b1011 '
b1011 9
#550
b1101 !
b1101 (
1.
1%
#560
0"
17
0*
0)
0+
01
14
b1101 !
b1101 (
1.
0-
00
13
0%
b1100 $
b1100 '
b1100 9
#570
11
1+
b1110 !
b1110 (
0.
1%
#580
11
1+
b1110 !
b1110 (
0.
1-
0%
b1101 $
b1101 '
b1101 9
#590
b1111 !
b1111 (
1.
1%
#600
0"
17
0)
14
0*
0+
11
b1111 !
b1111 (
1.
0-
10
0%
b1110 $
b1110 '
b1110 9
#610
1"
07
1)
04
1*
01
1+
b0 !
b0 (
0.
1%
#620
1"
07
1)
04
1*
01
1+
b0 !
b0 (
0.
1-
0%
b1111 $
b1111 '
b1111 9
#630
b1 !
b1 (
1.
1%
#640
0*
11
0)
0"
0+
04
07
b10 !
b10 (
0.
0-
00
03
06
0,
1/
0%
b0 $
b0 '
b10 #
b10 &
b10 8
b0 9
#650
b11 !
b11 (
1.
1%
#660
b11 !
b11 (
1.
1-
0%
b1 $
b1 '
b1 9
#670
14
1*
01
1+
b100 !
b100 (
0.
1%
#680
0+
01
b100 !
b100 (
0.
0-
10
0%
b10 $
b10 '
b10 9
#690
b101 !
b101 (
1.
1%
#700
b101 !
b101 (
1.
1-
0%
b11 $
b11 '
b11 9
#710
11
1+
b110 !
b110 (
0.
1%
#720
0*
07
0)
0+
11
14
b110 !
b110 (
0.
0-
00
13
0%
b100 $
b100 '
b100 9
#730
b111 !
b111 (
1.
1%
#740
b111 !
b111 (
1.
1-
0%
b101 $
b101 '
b101 9
#750
17
1)
04
1*
01
1+
b1000 !
b1000 (
0.
1%
#760
0+
01
b1000 !
b1000 (
0.
0-
10
0%
b110 $
b110 '
b110 9
#770
b1001 !
b1001 (
1.
1%
#780
b1001 !
b1001 (
1.
1-
0%
b111 $
b111 '
b111 9
#790
11
1+
b1010 !
b1010 (
0.
1%
#800
0*
0)
0"
0+
11
04
17
b1010 !
b1010 (
0.
0-
00
03
16
0%
b1000 $
b1000 '
b1000 9
#810
b1011 !
b1011 (
1.
1%
#820
b1011 !
b1011 (
1.
1-
0%
b1001 $
b1001 '
b1001 9
#830
14
1*
01
1+
b1100 !
b1100 (
0.
1%
#840
0+
01
b1100 !
b1100 (
0.
0-
10
0%
b1010 $
b1010 '
b1010 9
#850
b1101 !
b1101 (
1.
1%
#860
b1101 !
b1101 (
1.
1-
0%
b1011 $
b1011 '
b1011 9
#870
11
1+
b1110 !
b1110 (
0.
1%
#880
0"
0*
17
0)
0+
11
14
b1110 !
b1110 (
0.
0-
00
13
0%
b1100 $
b1100 '
b1100 9
#890
b1111 !
b1111 (
1.
1%
#900
b1111 !
b1111 (
1.
1-
0%
b1101 $
b1101 '
b1101 9
#910
1"
07
1)
04
1*
01
1+
b0 !
b0 (
0.
1%
#920
0+
01
b0 !
b0 (
0.
0-
10
0%
b1110 $
b1110 '
b1110 9
#930
b1 !
b1 (
1.
1%
#940
b1 !
b1 (
1.
1-
0%
b1111 $
b1111 '
b1111 9
#950
11
1+
b10 !
b10 (
0.
1%
#960
0*
0)
0"
0+
11
04
07
b11 !
b11 (
1.
0-
00
03
06
1,
0%
b0 $
b0 '
b11 #
b11 &
b11 8
b0 9
#970
14
1*
01
1+
b100 !
b100 (
0.
1%
#980
14
1*
01
1+
b100 !
b100 (
0.
1-
0%
b1 $
b1 '
b1 9
#990
b101 !
b101 (
1.
1%
#1000
0+
01
b101 !
b101 (
1.
0-
10
0%
b10 $
b10 '
b10 9
#1010
11
1+
b110 !
b110 (
0.
1%
#1020
11
1+
b110 !
b110 (
0.
1-
0%
b11 $
b11 '
b11 9
#1030
b111 !
b111 (
1.
1%
#1040
0*
07
0)
0+
11
14
b111 !
b111 (
1.
0-
00
13
0%
b100 $
b100 '
b100 9
#1050
17
1)
04
1*
01
1+
b1000 !
b1000 (
0.
1%
#1060
17
1)
04
1*
01
1+
b1000 !
b1000 (
0.
1-
0%
b101 $
b101 '
b101 9
#1070
b1001 !
b1001 (
1.
1%
#1080
0+
01
b1001 !
b1001 (
1.
0-
10
0%
b110 $
b110 '
b110 9
#1090
11
1+
b1010 !
b1010 (
0.
1%
#1100
11
1+
b1010 !
b1010 (
0.
1-
0%
b111 $
b111 '
b111 9
#1110
b1011 !
b1011 (
1.
1%
#1120
0*
0)
0"
0+
11
04
17
b1011 !
b1011 (
1.
0-
00
03
16
0%
b1000 $
b1000 '
b1000 9
#1130
14
1*
01
1+
b1100 !
b1100 (
0.
1%
#1140
14
1*
01
1+
b1100 !
b1100 (
0.
1-
0%
b1001 $
b1001 '
b1001 9
#1150
b1101 !
b1101 (
1.
1%
#1160
0+
01
b1101 !
b1101 (
1.
0-
10
0%
b1010 $
b1010 '
b1010 9
#1170
11
1+
b1110 !
b1110 (
0.
1%
#1180
11
1+
b1110 !
b1110 (
0.
1-
0%
b1011 $
b1011 '
b1011 9
#1190
b1111 !
b1111 (
1.
1%
#1200
0"
0*
17
0)
0+
11
14
b1111 !
b1111 (
1.
0-
00
13
0%
b1100 $
b1100 '
b1100 9
#1210
1"
07
1)
04
1*
01
1+
b0 !
b0 (
0.
1%
#1220
1"
07
1)
04
1*
01
1+
b0 !
b0 (
0.
1-
0%
b1101 $
b1101 '
b1101 9
#1230
b1 !
b1 (
1.
1%
#1240
0+
01
b1 !
b1 (
1.
0-
10
0%
b1110 $
b1110 '
b1110 9
#1250
11
1+
b10 !
b10 (
0.
1%
#1260
11
1+
b10 !
b10 (
0.
1-
0%
b1111 $
b1111 '
b1111 9
#1270
b11 !
b11 (
1.
1%
#1280
0)
14
01
0"
0*
0+
07
b100 !
b100 (
0.
0-
00
03
06
0,
0/
12
0%
b0 $
b0 '
b100 #
b100 &
b100 8
b0 9
#1290
b101 !
b101 (
1.
1%
#1300
b101 !
b101 (
1.
1-
0%
b1 $
b1 '
b1 9
#1310
11
1+
b110 !
b110 (
0.
1%
#1320
07
0)
14
0*
0+
11
b110 !
b110 (
0.
0-
10
0%
b10 $
b10 '
b10 9
#1330
b111 !
b111 (
1.
1%
#1340
b111 !
b111 (
1.
1-
0%
b11 $
b11 '
b11 9
#1350
17
1)
04
1*
01
1+
b1000 !
b1000 (
0.
1%
#1360
0*
0+
01
04
b1000 !
b1000 (
0.
0-
00
13
0%
b100 $
b100 '
b100 9
#1370
b1001 !
b1001 (
1.
1%
#1380
b1001 !
b1001 (
1.
1-
0%
b101 $
b101 '
b101 9
#1390
11
1+
b1010 !
b1010 (
0.
1%
#1400
04
0*
0+
11
b1010 !
b1010 (
0.
0-
10
0%
b110 $
b110 '
b110 9
#1410
b1011 !
b1011 (
1.
1%
#1420
b1011 !
b1011 (
1.
1-
0%
b111 $
b111 '
b111 9
#1430
14
1*
01
1+
b1100 !
b1100 (
0.
1%
#1440
0)
0*
0"
0+
01
14
17
b1100 !
b1100 (
0.
0-
00
03
16
0%
b1000 $
b1000 '
b1000 9
#1450
b1101 !
b1101 (
1.
1%
#1460
b1101 !
b1101 (
1.
1-
0%
b1001 $
b1001 '
b1001 9
#1470
11
1+
b1110 !
b1110 (
0.
1%
#1480
0"
17
0)
14
0*
0+
11
b1110 !
b1110 (
0.
0-
10
0%
b1010 $
b1010 '
b1010 9
#1490
b1111 !
b1111 (
1.
1%
#1500
b1111 !
b1111 (
1.
1-
0%
b1011 $
b1011 '
b1011 9
#1510
1"
07
1)
04
1*
01
1+
b0 !
b0 (
0.
1%
#1520
0*
0+
01
04
b0 !
b0 (
0.
0-
00
13
0%
b1100 $
b1100 '
b1100 9
#1530
b1 !
b1 (
1.
1%
#1540
b1 !
b1 (
1.
1-
0%
b1101 $
b1101 '
b1101 9
#1550
11
1+
b10 !
b10 (
0.
1%
#1560
04
0*
0+
11
b10 !
b10 (
0.
0-
10
0%
b1110 $
b1110 '
b1110 9
#1570
b11 !
b11 (
1.
1%
#1580
b11 !
b11 (
1.
1-
0%
b1111 $
b1111 '
b1111 9
#1590
14
1*
01
1+
b100 !
b100 (
0.
1%
#1600
0)
0*
0"
0+
01
14
07
b101 !
b101 (
1.
0-
00
03
06
1,
0%
b0 $
b0 '
b101 #
b101 &
b101 8
b0 9
#1610
11
1+
b110 !
b110 (
0.
1%
#1620
11
1+
b110 !
b110 (
0.
1-
0%
b1 $
b1 '
b1 9
#1630
b111 !
b111 (
1.
1%
#1640
07
0)
14
0*
0+
11
b111 !
b111 (
1.
0-
10
0%
b10 $
b10 '
b10 9
#1650
17
1)
04
1*
01
1+
b1000 !
b1000 (
0.
1%
#1660
17
1)
04
1*
01
1+
b1000 !
b1000 (
0.
1-
0%
b11 $
b11 '
b11 9
#1670
b1001 !
b1001 (
1.
1%
#1680
0*
0+
01
04
b1001 !
b1001 (
1.
0-
00
13
0%
b100 $
b100 '
b100 9
#1690
11
1+
b1010 !
b1010 (
0.
1%
#1700
11
1+
b1010 !
b1010 (
0.
1-
0%
b101 $
b101 '
b101 9
#1710
b1011 !
b1011 (
1.
1%
#1720
04
0*
0+
11
b1011 !
b1011 (
1.
0-
10
0%
b110 $
b110 '
b110 9
#1730
14
1*
01
1+
b1100 !
b1100 (
0.
1%
#1740
14
1*
01
1+
b1100 !
b1100 (
0.
1-
0%
b111 $
b111 '
b111 9
#1750
b1101 !
b1101 (
1.
1%
#1760
0)
0*
0"
0+
01
14
17
b1101 !
b1101 (
1.
0-
00
03
16
0%
b1000 $
b1000 '
b1000 9
#1770
11
1+
b1110 !
b1110 (
0.
1%
#1780
11
1+
b1110 !
b1110 (
0.
1-
0%
b1001 $
b1001 '
b1001 9
#1790
b1111 !
b1111 (
1.
1%
#1800
0"
17
0)
14
0*
0+
11
b1111 !
b1111 (
1.
0-
10
0%
b1010 $
b1010 '
b1010 9
#1810
1"
07
1)
04
1*
01
1+
b0 !
b0 (
0.
1%
#1820
1"
07
1)
04
1*
01
1+
b0 !
b0 (
0.
1-
0%
b1011 $
b1011 '
b1011 9
#1830
b1 !
b1 (
1.
1%
#1840
0*
0+
01
04
b1 !
b1 (
1.
0-
00
13
0%
b1100 $
b1100 '
b1100 9
#1850
11
1+
b10 !
b10 (
0.
1%
#1860
11
1+
b10 !
b10 (
0.
1-
0%
b1101 $
b1101 '
b1101 9
#1870
b11 !
b11 (
1.
1%
#1880
04
0*
0+
11
b11 !
b11 (
1.
0-
10
0%
b1110 $
b1110 '
b1110 9
#1890
14
1*
01
1+
b100 !
b100 (
0.
1%
#1900
14
1*
01
1+
b100 !
b100 (
0.
1-
0%
b1111 $
b1111 '
b1111 9
#1910
b101 !
b101 (
1.
1%
#1920
0)
0*
11
0"
0+
14
07
b110 !
b110 (
0.
0-
00
03
06
0,
1/
0%
b0 $
b0 '
b110 #
b110 &
b110 8
b0 9
#1930
b111 !
b111 (
1.
1%
#1940
b111 !
b111 (
1.
1-
0%
b1 $
b1 '
b1 9
#1950
17
1)
04
1*
01
1+
b1000 !
b1000 (
0.
1%
#1960
0+
01
b1000 !
b1000 (
0.
0-
10
0%
b10 $
b10 '
b10 9
#1970
b1001 !
b1001 (
1.
1%
#1980
b1001 !
b1001 (
1.
1-
0%
b11 $
b11 '
b11 9
#1990
11
1+
b1010 !
b1010 (
0.
1%
#2000
0*
0+
11
04
b1010 !
b1010 (
0.
0-
00
13
0%
b100 $
b100 '
b100 9
#2010
b1011 !
b1011 (
1.
1%
#2020
b1011 !
b1011 (
1.
1-
0%
b101 $
b101 '
b101 9
#2030
14
1*
01
1+
b1100 !
b1100 (
0.
1%
#2040
0+
01
b1100 !
b1100 (
0.
0-
10
0%
b110 $
b110 '
b110 9
#2050
b1101 !
b1101 (
1.
1%
#2060
b1101 !
b1101 (
1.
1-
0%
b111 $
b111 '
b111 9
#2070
11
1+
b1110 !
b1110 (
0.
1%
#2080
0)
0*
0"
0+
11
14
17
b1110 !
b1110 (
0.
0-
00
03
16
0%
b1000 $
b1000 '
b1000 9
#2090
b1111 !
b1111 (
1.
1%
#2100
b1111 !
b1111 (
1.
1-
0%
b1001 $
b1001 '
b1001 9
#2110
1"
07
1)
04
1*
01
1+
b0 !
b0 (
0.
1%
#2120
0+
01
b0 !
b0 (
0.
0-
10
0%
b1010 $
b1010 '
b1010 9
#2130
b1 !
b1 (
1.
1%
#2140
b1 !
b1 (
1.
1-
0%
b1011 $
b1011 '
b1011 9
#2150
11
1+
b10 !
b10 (
0.
1%
#2160
0*
0+
11
04
b10 !
b10 (
0.
0-
00
13
0%
b1100 $
b1100 '
b1100 9
#2170
b11 !
b11 (
1.
1%
#2180
b11 !
b11 (
1.
1-
0%
b1101 $
b1101 '
b1101 9
#2190
14
1*
01
1+
b100 !
b100 (
0.
1%
#2200
0+
01
b100 !
b100 (
0.
0-
10
0%
b1110 $
b1110 '
b1110 9
#2210
b101 !
b101 (
1.
1%
#2220
b101 !
b101 (
1.
1-
0%
b1111 $
b1111 '
b1111 9
#2230
11
1+
b110 !
b110 (
0.
1%
#2240
0)
0*
0"
0+
11
14
07
b111 !
b111 (
1.
0-
00
03
06
1,
0%
b0 $
b0 '
b111 #
b111 &
b111 8
b0 9
#2250
17
1)
04
1*
01
1+
b1000 !
b1000 (
0.
1%
#2260
17
1)
04
1*
01
1+
b1000 !
b1000 (
0.
1-
0%
b1 $
b1 '
b1 9
#2270
b1001 !
b1001 (
1.
1%
#2280
0+
01
b1001 !
b1001 (
1.
0-
10
0%
b10 $
b10 '
b10 9
#2290
11
1+
b1010 !
b1010 (
0.
1%
#2300
11
1+
b1010 !
b1010 (
0.
1-
0%
b11 $
b11 '
b11 9
#2310
b1011 !
b1011 (
1.
1%
#2320
0*
0+
11
04
b1011 !
b1011 (
1.
0-
00
13
0%
b100 $
b100 '
b100 9
#2330
14
1*
01
1+
b1100 !
b1100 (
0.
1%
#2340
14
1*
01
1+
b1100 !
b1100 (
0.
1-
0%
b101 $
b101 '
b101 9
#2350
b1101 !
b1101 (
1.
1%
#2360
0+
01
b1101 !
b1101 (
1.
0-
10
0%
b110 $
b110 '
b110 9
#2370
11
1+
b1110 !
b1110 (
0.
1%
#2380
11
1+
b1110 !
b1110 (
0.
1-
0%
b111 $
b111 '
b111 9
#2390
b1111 !
b1111 (
1.
1%
#2400
0)
0*
0"
0+
11
14
17
b1111 !
b1111 (
1.
0-
00
03
16
0%
b1000 $
b1000 '
b1000 9
#2410
1"
07
1)
04
1*
01
1+
b0 !
b0 (
0.
1%
#2420
1"
07
1)
04
1*
01
1+
b0 !
b0 (
0.
1-
0%
b1001 $
b1001 '
b1001 9
#2430
b1 !
b1 (
1.
1%
#2440
0+
01
b1 !
b1 (
1.
0-
10
0%
b1010 $
b1010 '
b1010 9
#2450
11
1+
b10 !
b10 (
0.
1%
#2460
11
1+
b10 !
b10 (
0.
1-
0%
b1011 $
b1011 '
b1011 9
#2470
b11 !
b11 (
1.
1%
#2480
0*
0+
11
04
b11 !
b11 (
1.
0-
00
13
0%
b1100 $
b1100 '
b1100 9
#2490
14
1*
01
1+
b100 !
b100 (
0.
1%
#2500
14
1*
01
1+
b100 !
b100 (
0.
1-
0%
b1101 $
b1101 '
b1101 9
#2510
b101 !
b101 (
1.
1%
#2520
0+
01
b101 !
b101 (
1.
0-
10
0%
b1110 $
b1110 '
b1110 9
#2530
11
1+
b110 !
b110 (
0.
1%
#2540
11
1+
b110 !
b110 (
0.
1-
0%
b1111 $
b1111 '
b1111 9
#2550
b111 !
b111 (
1.
1%
#2560
0"
04
17
01
0*
0)
0+
b1000 !
b1000 (
0.
0-
00
03
06
0,
0/
02
15
0%
b0 $
b0 '
b1000 #
b1000 &
b1000 8
b0 9
#2570
b1001 !
b1001 (
1.
1%
#2580
b1001 !
b1001 (
1.
1-
0%
b1 $
b1 '
b1 9
#2590
11
1+
b1010 !
b1010 (
0.
1%
#2600
04
0*
0+
11
b1010 !
b1010 (
0.
0-
10
0%
b10 $
b10 '
b10 9
#2610
b1011 !
b1011 (
1.
1%
#2620
b1011 !
b1011 (
1.
1-
0%
b11 $
b11 '
b11 9
#2630
14
1*
01
1+
b1100 !
b1100 (
0.
1%
#2640
0"
17
0*
0)
0+
01
14
b1100 !
b1100 (
0.
0-
00
13
0%
b100 $
b100 '
b100 9
#2650
b1101 !
b1101 (
1.
1%
#2660
b1101 !
b1101 (
1.
1-
0%
b101 $
b101 '
b101 9
#2670
11
1+
b1110 !
b1110 (
0.
1%
#2680
0"
17
0)
14
0*
0+
11
b1110 !
b1110 (
0.
0-
10
0%
b110 $
b110 '
b110 9
#2690
b1111 !
b1111 (
1.
1%
#2700
b1111 !
b1111 (
1.
1-
0%
b111 $
b111 '
b111 9
#2710
1"
07
1)
04
1*
01
1+
b0 !
b0 (
0.
1%
#2720
0*
0)
0+
01
04
07
b0 !
b0 (
0.
0-
00
03
16
0%
b1000 $
b1000 '
b1000 9
#2730
b1 !
b1 (
1.
1%
#2740
b1 !
b1 (
1.
1-
0%
b1001 $
b1001 '
b1001 9
#2750
11
1+
b10 !
b10 (
0.
1%
#2760
04
0*
0+
11
b10 !
b10 (
0.
0-
10
0%
b1010 $
b1010 '
b1010 9
#2770
b11 !
b11 (
1.
1%
#2780
b11 !
b11 (
1.
1-
0%
b1011 $
b1011 '
b1011 9
#2790
14
1*
01
1+
b100 !
b100 (
0.
1%
#2800
07
0*
0)
0+
01
14
b100 !
b100 (
0.
0-
00
13
0%
b1100 $
b1100 '
b1100 9
#2810
b101 !
b101 (
1.
1%
#2820
b101 !
b101 (
1.
1-
0%
b1101 $
b1101 '
b1101 9
#2830
11
1+
b110 !
b110 (
0.
1%
#2840
07
0)
14
0*
0+
11
b110 !
b110 (
0.
0-
10
0%
b1110 $
b1110 '
b1110 9
#2850
b111 !
b111 (
1.
1%
#2860
b111 !
b111 (
1.
1-
0%
b1111 $
b1111 '
b1111 9
#2870
17
1)
04
1*
01
1+
b1000 !
b1000 (
0.
1%
#2880
0"
0*
0)
0+
01
04
17
b1001 !
b1001 (
1.
0-
00
03
06
1,
0%
b0 $
b0 '
b1001 #
b1001 &
b1001 8
b0 9
#2890
11
1+
b1010 !
b1010 (
0.
1%
#2900
11
1+
b1010 !
b1010 (
0.
1-
0%
b1 $
b1 '
b1 9
#2910
b1011 !
b1011 (
1.
1%
#2920
04
0*
0+
11
b1011 !
b1011 (
1.
0-
10
0%
b10 $
b10 '
b10 9
#2930
14
1*
01
1+
b1100 !
b1100 (
0.
1%
#2940
14
1*
01
1+
b1100 !
b1100 (
0.
1-
0%
b11 $
b11 '
b11 9
#2950
b1101 !
b1101 (
1.
1%
#2960
0"
17
0*
0)
0+
01
14
b1101 !
b1101 (
1.
0-
00
13
0%
b100 $
b100 '
b100 9
#2970
11
1+
b1110 !
b1110 (
0.
1%
#2980
11
1+
b1110 !
b1110 (
0.
1-
0%
b101 $
b101 '
b101 9
#2990
b1111 !
b1111 (
1.
1%
#3000
0"
17
0)
14
0*
0+
11
b1111 !
b1111 (
1.
0-
10
0%
b110 $
b110 '
b110 9
#3010
1"
07
1)
04
1*
01
1+
b0 !
b0 (
0.
1%
#3020
1"
07
1)
04
1*
01
1+
b0 !
b0 (
0.
1-
0%
b111 $
b111 '
b111 9
#3030
b1 !
b1 (
1.
1%
#3040
0*
0)
0+
01
04
07
b1 !
b1 (
1.
0-
00
03
16
0%
b1000 $
b1000 '
b1000 9
#3050
11
1+
b10 !
b10 (
0.
1%
#3060
11
1+
b10 !
b10 (
0.
1-
0%
b1001 $
b1001 '
b1001 9
#3070
b11 !
b11 (
1.
1%
#3080
04
0*
0+
11
b11 !
b11 (
1.
0-
10
0%
b1010 $
b1010 '
b1010 9
#3090
14
1*
01
1+
b100 !
b100 (
0.
1%
#3100
14
1*
01
1+
b100 !
b100 (
0.
1-
0%
b1011 $
b1011 '
b1011 9
#3110
b101 !
b101 (
1.
1%
#3120
07
0*
0)
0+
01
14
b101 !
b101 (
1.
0-
00
13
0%
b1100 $
b1100 '
b1100 9
#3130
11
1+
b110 !
b110 (
0.
1%
#3140
11
1+
b110 !
b110 (
0.
1-
0%
b1101 $
b1101 '
b1101 9
#3150
b111 !
b111 (
1.
1%
#3160
07
0)
14
0*
0+
11
b111 !
b111 (
1.
0-
10
0%
b1110 $
b1110 '
b1110 9
#3170
17
1)
04
1*
01
1+
b1000 !
b1000 (
0.
1%
#3180
17
1)
04
1*
01
1+
b1000 !
b1000 (
0.
1-
0%
b1111 $
b1111 '
b1111 9
#3190
b1001 !
b1001 (
1.
1%
#3200
0"
0*
11
0)
0+
04
17
b1010 !
b1010 (
0.
0-
00
03
06
0,
1/
0%
b0 $
b0 '
b1010 #
b1010 &
b1010 8
b0 9
#3210
b1011 !
b1011 (
1.
1%
#3220
b1011 !
b1011 (
1.
1-
0%
b1 $
b1 '
b1 9
#3230
14
1*
01
1+
b1100 !
b1100 (
0.
1%
#3240
0+
01
b1100 !
b1100 (
0.
0-
10
0%
b10 $
b10 '
b10 9
#3250
b1101 !
b1101 (
1.
1%
#3260
b1101 !
b1101 (
1.
1-
0%
b11 $
b11 '
b11 9
#3270
11
1+
b1110 !
b1110 (
0.
1%
#3280
0"
0*
17
0)
0+
11
14
b1110 !
b1110 (
0.
0-
00
13
0%
b100 $
b100 '
b100 9
#3290
b1111 !
b1111 (
1.
1%
#3300
b1111 !
b1111 (
1.
1-
0%
b101 $
b101 '
b101 9
#3310
1"
07
1)
04
1*
01
1+
b0 !
b0 (
0.
1%
#3320
0+
01
b0 !
b0 (
0.
0-
10
0%
b110 $
b110 '
b110 9
#3330
b1 !
b1 (
1.
1%
#3340
b1 !
b1 (
1.
1-
0%
b111 $
b111 '
b111 9
#3350
11
1+
b10 !
b10 (
0.
1%
#3360
0*
0)
0+
11
04
07
b10 !
b10 (
0.
0-
00
03
16
0%
b1000 $
b1000 '
b1000 9
#3370
b11 !
b11 (
1.
1%
#3380
b11 !
b11 (
1.
1-
0%
b1001 $
b1001 '
b1001 9
#3390
14
1*
01
1+
b100 !
b100 (
0.
1%
#3400
0+
01
b100 !
b100 (
0.
0-
10
0%
b1010 $
b1010 '
b1010 9
#3410
b101 !
b101 (
1.
1%
#3420
b101 !
b101 (
1.
1-
0%
b1011 $
b1011 '
b1011 9
#3430
11
1+
b110 !
b110 (
0.
1%
#3440
0*
07
0)
0+
11
14
b110 !
b110 (
0.
0-
00
13
0%
b1100 $
b1100 '
b1100 9
#3450
b111 !
b111 (
1.
1%
#3460
b111 !
b111 (
1.
1-
0%
b1101 $
b1101 '
b1101 9
#3470
17
1)
04
1*
01
1+
b1000 !
b1000 (
0.
1%
#3480
0+
01
b1000 !
b1000 (
0.
0-
10
0%
b1110 $
b1110 '
b1110 9
#3490
b1001 !
b1001 (
1.
1%
#3500
b1001 !
b1001 (
1.
1-
0%
b1111 $
b1111 '
b1111 9
#3510
11
1+
b1010 !
b1010 (
0.
1%
