Day04/magnitude_comparator.v
module magnitude_comparator(a, b, a_less_than_b, a_greater_than_b, a_equal_b);
    input [1:0] a, b;
    output a_less_than_b, a_greater_than_b, a_equal_b;

    assign a_less_than_b = (a < b);
    assign a_greater_than_b = (a > b);
    assign a_equal_b = (a == b);
endmodule

Day04/tb_magnitude_comparator.v
module tb_magnitude_comparator;
    reg [1:0] a, b;
    wire a_less_than_b, a_greater_than_b, a_equal_b;

    magnitude_comparator uut(
        .a(a), 
        .b(b), 
        .a_less_than_b(a_less_than_b), 
        .a_greater_than_b(a_greater_than_b), 
        .a_equal_b(a_equal_b)
        );

    initial begin
        $dumpfile("magnitude_comparator.vcd");
        $dumpvars(0, tb_magnitude_comparator);
        for (integer i = 0; i < 4; i = i + 1) 
        begin
            for (integer j = 0; j < 4; j = j + 1) 
            begin
                a = i; b = j; #10;
            end
        end
        $finish;
    end
endmodule

Day04/magnitude_comparator.vcd
$date
	Tue Jan 14 20:13:35 2025
$end
$version
	Icarus Verilog
$end
$timescale
	1s
$end
$scope module tb_magnitude_comparator $end
$var wire 1 ! a_less_than_b $end
$var wire 1 " a_greater_than_b $end
$var wire 1 # a_equal_b $end
$var reg 2 $ a [1:0] $end
$var reg 2 % b [1:0] $end
$scope module uut $end
$var wire 2 & a [1:0] $end
$var wire 2 ' b [1:0] $end
$var wire 1 ! a_less_than_b $end
$var wire 1 " a_greater_than_b $end
$var wire 1 # a_equal_b $end
$upscope $end
$scope begin $ivl_for_loop0 $end
$var integer 32 ( i [31:0] $end
$scope begin $ivl_for_loop1 $end
$var integer 32 ) j [31:0] $end
$upscope $end
$upscope $end
$upscope $end
$enddefinitions $end
$comment Show the parameter values. $end
$dumpall
$end
#0
$dumpvars
b0 )
b0 (
b0 '
b0 &
b0 %
b0 $
1#
0"
0!
$end
#10
1!
0#
b1 %
b1 '
b1 )
#20
b10 %
b10 '
b10 )
#30
b11 %
b11 '
b11 )
#40
0!
1"
b0 %
b0 '
b1 $
b1 &
b1 (
b0 )
#50
0"
1#
b1 %
b1 '
b1 )
#60
1!
0#
b10 %
b10 '
b10 )
#70
b11 %
b11 '
b11 )
#80
0!
1"
b0 %
b0 '
b10 $
b10 &
b10 (
b0 )
#90
b1 %
b1 '
b1 )
#100
0"
1#
b10 %
b10 '
b10 )
#110
1!
0#
b11 %
b11 '
b11 )
#120
1"
b0 %
b0 '
0!
0#
b11 $
b11 &
b11 (
b0 )
#130
b1 %
b1 '
b1 )
#140
b10 %
b10 '
b10 )
#150
0"
1#
b11 %
b11 '
b11 )
#160
b100 (
b100 )
