Day05/decoder3to8.v
module decoder3to8 (
    input wire [2:0] a,     
    input wire en,          
    output reg [7:0] y     
);

    always @(*) begin
        if (en) begin
            y = 8'b00000000;      
            y[a] = 1'b1;          
        end 
        else begin
            y = 8'b00000000;      
        end
    end

endmodule

Day05/testbench.v
`timescale 1ns / 1ps

module tb_decoder3to8;

    reg [2:0] a;           
    reg en;                
    wire [7:0] y;         

    // Instantiate the decoder module
    decoder3to8 uut (
        .a(a),
        .en(en),
        .y(y)
    );

    integer i;

    initial begin
        $dumpfile("decoder3to8.vcd");
        $dumpvars(0, tb_decoder3to8);

        en = 1'b0; a = 3'b000;

        #10 en = 1'b0; a = 3'b000; // Outputs should remain 0
        #10 en = 1'b0; a = 3'b101; // Outputs should remain 0

        // Test with enable signal ON
        en = 1'b1;
        for (i = 0; i < 8; i = i + 1) begin
            #10 a = i; // Change input and observe output
        end

        // Disable enable signal and check outputs
        #10 en = 1'b0; a = 3'b011; // Outputs should remain 0

        #10 $finish; // End simulation
    end

endmodule

Day05/decoder3to8.vcd
$date
	Wed Jan 15 10:04:57 2025
$end
$version
	Icarus Verilog
$end
$timescale
	1ps
$end
$scope module tb_decoder3to8 $end
$var wire 8 ! y [7:0] $end
$var reg 3 " a [2:0] $end
$var reg 1 # en $end
$var integer 32 $ i [31:0] $end
$scope module uut $end
$var wire 3 % a [2:0] $end
$var wire 1 # en $end
$var reg 8 & y [7:0] $end
$upscope $end
$upscope $end
$enddefinitions $end
$comment Show the parameter values. $end
$dumpall
$end
#0
$dumpvars
b0 &
b0 %
bx $
0#
b0 "
b0 !
$end
#20000
b100000 !
b100000 &
b0 $
1#
b101 "
b101 %
#30000
b1 !
b1 &
b1 $
b0 "
b0 %
#40000
b10 !
b10 &
b10 $
b1 "
b1 %
#50000
b100 !
b100 &
b11 $
b10 "
b10 %
#60000
b1000 !
b1000 &
b100 $
b11 "
b11 %
#70000
b10000 !
b10000 &
b101 $
b100 "
b100 %
#80000
b100000 !
b100000 &
b110 $
b101 "
b101 %
#90000
b1000000 !
b1000000 &
b111 $
b110 "
b110 %
#100000
b10000000 !
b10000000 &
b1000 $
b111 "
b111 %
#110000
b0 !
b0 &
b11 "
b11 %
0#
